ssb_optimize/__init__.py
ssb_optimize/optimizer.py
test/__init__.py
test/constraint_functions.py
test/objective_functions.py
test/test_bounded_constrained_nelder_mead.py
test/test_bounded_constrained_particle_swarm.py
test/test_bounds_constraints.py
test/test_least_squares.py
test/test_nelder_mead.py
test/test_particle_swarm.py
ssb_optimize-0.1.3.dist-info/METADATA
ssb_optimize-0.1.3.dist-info/WHEEL
ssb_optimize-0.1.3.dist-info/license.txt
ssb_optimize-0.1.3.dist-info/top_level.txt
ssb_optimize-0.1.3.dist-info/RECORD
