Metadata-Version: 2.1
Name: ssb-optimize
Version: 0.1.3
Summary: Particle Swarm and Nelder-Mead Simplex optimization algorithms with Least Squares Regression and Bootstrap confidence intervals.
Home-page: https://github.com/theleftcoast/swarm-simplex-bootstrap
Author: John Towne
Author-email: towne.john@gmail.com
License: UNKNOWN
Platform: UNKNOWN
Classifier: Programming Language :: Python :: 3
Classifier: License :: OSI Approved :: BSD License
Classifier: Operating System :: OS Independent
Requires-Python: >=3.6
Requires-Dist: numpy
